setup.py
cake/__init__.py
cake/icing.py
cake/sponge.py
kkermylib.egg-info/PKG-INFO
kkermylib.egg-info/SOURCES.txt
kkermylib.egg-info/dependency_links.txt
kkermylib.egg-info/top_level.txt