Metadata-Version: 1.0
Name: kkermylib
Version: 1.0
Summary: just a simple test
Home-page: UNKNOWN
Author: kker
Author-email: kkerneo@gmail.com
License: MIT License
Keywords: simple,test
Platform: any
